{"id":"00075cfc99a-353e-4e8b-9c75-d5c290421665","created":0,"title":"南瓜泥善治久咳不止","description":"南瓜泥善治久咳不止\n父亲连续咳嗽了近一个月，吃了多种止咳药都未见疗效。后来，亲戚告诉了我一条专治久咳不止的偏方，父亲服用一段时间后，咳嗽渐渐变少了。\n方法：取南瓜250克，蜂蜜15克。先将南瓜洗净、去皮和囊，切块，放进锅里蒸20分钟。蒸熟后捣泥放凉，加蜂蜜15克拌匀备用。早晚饭前空腹吃5克即可。\n点评：南瓜性味甘、温，无毒，入脾、胃经，有润肺益气、化痰、消炎止痛、降低血糖、驱虫解毒、止喘、美容等功效，主治肺痈、哮证、脾虚气弱等。而蜂蜜有润肺止咳、润肠通便、润肤生肌及解毒的功效，适宜肺燥咳嗽、干咳无痰的人食用。两者合用，能化痰止咳、润肺解毒，适合肺燥咳嗽者食用。\n（摘自《老人报》乔志强 文）\n","categoryId":"000589d37f1-3184-4e5b-ae0d-93ba7606277d","publisherId":null,"applicationId":null,"type":null,"tags":null,"url":"/2016/03/12513.html"}