{"id":"000098aee44-60d6-45ab-8732-6d98aa062403","created":0,"title":"香蕉冰糖止咳特效","description":"    大概有三年的时间，每逢入秋以后，我就咳嗽不止，虽经赴医院诊治，仍是只能治标、不能治本。由于喉咙经常搔痒，我被迫必须随身携带一小瓶水，以便喉咙发痒时，能以水止痒（喝了水后，痒即止住）。就这样，每年秋冬两季，我就断断续续为咳嗽所苦。    去年夏天，我参加了一场医学研讨会，与旁边一名学员谈及我的咳嗽问题，她很含蓄的建议我用香蕉炖冰糖试吃。她说，此方已有不少人治好常年咳。\n    香蕉炖冰糖能治常年咳？我半信半疑。但由于所费不多，且做法也不复杂，因此就尝试着试服，没料到，一个礼拜以后，咳嗽尽除。为了「乘胜追击」，我又续服了几天，没想不但那年冬天不再咳嗽，今年虽已入秋，亦未有「咳相」，直觉认为应是有效的良方，特将疗法予以披露：\n    购香蕉二或三条、冰糖一至 二两 。先将香蕉切成一寸大小的小块（去皮），再将冰糖捣碎，然后置于碗中，加入半碗水，之后放入锅中，隔水炖煮约十分钟，待冰糖溶化并冷却后食用。此时的香蕉虽然又烂又涩，很难下咽，但却能对咳嗽发挥奇效。\n    此种疗法，每晚一次，一周即可见效。 \n","categoryId":"000589d37f1-3184-4e5b-ae0d-93ba7606277d","publisherId":null,"applicationId":null,"type":null,"tags":null,"url":"/2012/08/7227.html"}