{"id":"000e2abda4d-c251-404d-a40e-e75f39964c50","created":0,"title":"风湿病偏方-林树森献方","description":"风湿病偏方\n　　求方回音\n　　风湿病，是东北常见病。每天，都有读者，发短信、邮件，寻求此病偏方。患者的痛苦，有重有轻。有的，起不来床，有的，疼得拿不住东西。有的，大夏天，还得穿线裤。有的人，被病折磨的，想了结此生。　　自开办以来，也登过多个治疗此病的方子。方子，不怕多。近日，新村的林师傅，又给记者献了一个治此病的偏方。老话讲，冬病夏治。如果有患者，还在被此病折磨，这个季节，正好可用此方治病。　　林树森献方　　处方：　　木瓜75克、川芎30克、牛夕30克、当归45克、五加皮45克、红花30克、续断30克、茄根30克、秦艽30克、防风30克、桑枝75克、独活30克、威灵仙45克、白花蛇30克、栀子30克、冰糖100克、天麻45克、玉竹35克、千年健30克　　用法：　　会喝酒的患者，将以上药物泡在10斤酒里。泡上三天后，开始服用。患者，每顿饭前喝一盅。10斤酒喝完，风湿便能治愈。不会喝酒的人，将冰糖砸碎，与其他药物一起研成面。患者每天，取半小勺药面，用温水冲服。一天三次，直至喝好为止。　　治疗病例　　这个方子，是林树森自己研究出来的。至今，此方已治愈了十几个人的风湿病。最早，验证此方的，是林师傅的老伴。早些年，大庆的条件艰苦。　　初来大庆创业时，林师傅和爱人的居住环境，非常差。林师傅，身体好，抵抗力强。可他的老伴，身子虚，不久就染上了病。她的病，就是常见的东北病——风湿。当时，林师傅的爱人年轻。这病，也没把她咋地。只不过，阴天下雨，隔三差五地，有那么一点点疼痛。　　等她上了岁数，年过50后，风湿病，开始在她身上“作妖”。先是风湿性关节炎，弄得她走不了道。后来，又得上了类风湿性关节炎，手指抓握，用不上劲。看到这种情况，当儿女的着急，林师傅更着急。同样作为老年人，林师傅知道，这病，对他们这个年龄的人，有多痛苦。他决心，为老伴治愈这种病。别人有这种想法，大家听起来，有点吹牛。可林师傅，与医学打了半辈子交道。　　他研究方子，是有根有据的，绝不瞎整。能祛风祛寒的药物，林师傅都收集起来。从这些药中，他甄选筛别，挑出了几种可行的。最后，他留出了19种，用来泡酒。泡好后，他就让老伴喝。　　老伴没等喝，却遭到小外孙的阻拦。小外孙，才三岁。从小，他由姥姥带大，跟姥姥的感情，特别好。小外孙，不让姥姥喝，怕姥姥被药着。姥姥说，没事，姥爷配的药，不会药姥姥的。这么说，外孙也不干。他让姥爷先喝。　　林师傅喝了，外孙看没事，才让姥姥喝。当时，林师傅配的药，是方中药量的一倍。他老伴，不能喝酒，林师傅就把药研成面，让她冲水喝。没想到，老伴只喝了半服药，风湿就好了。　　后来，这个方子，在林师傅的朋友圈中传开了。只要有这病的，都用这个方子。这个方子，也“争气”。按林师傅话说，“治一个保一个”。　　药理分析　　风湿，顾名思义，是风和湿两种病邪，结合所致的病症。当其侵入关节，就会造成风湿性关节炎、类风湿性关节炎。所以，治疗此病，在于祛风寒、祛湿。　　方中药物，茄根、红花、当归等，都有活血功效。血液运行通畅，有利于病情治疗。防风，可祛风解表，胜湿止痛。独活，可疏风解毒，活血祛淤。这些药，都是治风湿病的良药。在林师傅手里，它们经过合理搭配，就会最大程度地发挥药效。　　温馨提示　　使用此方，患者可按病情轻重，灵活掌握。病情重的患者，前期多喝一些。如果，感觉渐好，可慢慢减量。病情轻的患者，之前，就可以少喝一些，药没用完，就能治愈。\n","categoryId":"000124c1a30-8944-4d43-b46c-97fdd7ee6a86","publisherId":null,"applicationId":null,"type":null,"tags":null,"url":"/2012/12/8467.html"}