{"id":"00053a87820-5a95-49a9-bd58-878fa85fcc63","created":0,"title":"足跟痛偏方-靳国权献方","description":"足跟痛偏方\n　　靳国权献方　　处方：凡士林、火罐用法：在足跟痛部位，抹上点凡士林。然后，用一个小点的火罐，在痛处拔。每次，坚持拔40分钟以上。隔一天，再拔一次。一般患者，10天之内足跟就不痛了。　　治疗病例　　靳国权，是位按摩师。按摩过程中，他常接触到足跟痛的病人。起初，他靠按摩缓解疼痛。可这样的病人，不坚持按上几个月，很难治愈。病人，钱没少花，罪也没少遭。后来，他就自己琢磨，寻思有没有其他的治疗手段。通过分析，靳国权发现，足根痛病人，都是足根有炎症。这种炎症，有老损引起、有骨刺引发，还有的肾虚患者，体重太大，也容易引发足根痛。所以，消除炎症，才是治病根本。咋能消除炎症？靳国权，想到了火罐。拔火罐，能活血、通络，去除炎症。他把这个想法，跟一个熟悉的病人说了。这个病人，50多岁。46岁之后，她就开始渐渐发胖。到了50岁，她的体重，增加了20斤。因此一走起路来，就感到足跟疼痛。她吃了不少药，这病也没治好。后来，她找到了靳国权按摩，才感觉好些。可过一阵，又开始疼。后来，靳国权决定在她身上试一试自己的发明。那位女士，觉得拔火罐，也伤不到啥，就同意他这么做。每隔两天，她就来拔一次。过了10天后，她的脚后跟，奇迹般地不疼了。如今，已经过了5年时间，她的体重没变，可脚后跟，再也没疼过。药理分析引发足根疼痛的原因，挺多。脚跟脂肪垫老损，能引起足跟发炎、疼痛；足根有骨刺、骨质增生，也能引起足跟疼痛；体重增加，也是引发此病的病因。这个方子，对这三类情况，都适用。足跟部位，不好拔火罐。抹上凡士林，可增强吸力，让火罐更好吸附。而火罐，能改进血液循环，消除炎症。炎症却除了，足跟自然就不痛了。温馨提示40岁以上的女性，如果身体发福，足跟压力增加，就容易患上足跟痛。此时的女性，应该经常进行足跟按摩。按摩时，先轻后重，一点点加力。这样，有利于去除粘连部位，活血通络。\n","categoryId":"000124c1a30-8944-4d43-b46c-97fdd7ee6a86","publisherId":null,"applicationId":null,"type":null,"tags":null,"url":"/2012/12/8362.html"}