{"id":"000ef166269-5c3b-49b6-81fe-7c89b8c9cf0a","created":0,"title":"老年性前列腺肥大治疗秘方偏方","description":"    前列腺肥大，又称前列腺增生，属中医“癃闭”范畴。本病多发于老年人，中青年人亦有发生。证见小便不通或不利。若伴见头脑晕胀、口渴、呼吸急促、心烦、小腹胀痛、舌红苔黄、脉弦数，多为三焦火盛；咽干烦渴，呼吸急促，苔黄、脉数者，多属肺热气皇。\n《疏肝散结方治老年性前列腺肥大》\n【方剂】 柴胡、牛膝各10克，生牡蛎（先煎）30克，丹参、当归、赤芍、海浮石（先煎）、海藻、昆布、夏枯草、玄参各15克，川贝粉（分冲）3克，肾精子5 粒（肾精子即牛膀胧之结石，以桂圆肉包裹，于第1次服药时吞服）。\n【制用法】 水煎服，每日1剂。\n【功效】 治疗老年性前列腺肥大。\n【验证】 李xx ，男，78岁，1980年诊治。素有高血压史，又患小便淋漓不尽多年。1年前，因突然不能排尿急诊人北京x 医院治疗。经查诊断为“老年性前列腺肥大”。因血压高不适于手术，故作留置导尿管处理，并建议求治中医。经多方医治，效果不显。尿管长期留置，常常诱发尿道感染。故1年之中，几经住院治疗，甚感痛苦。患者形体瘦弱，精神萎靡，舌苔黄腻，脉弦重按有力。乃投以疏肝散结方，5剂。服药2剂后，自觉诸症减轻，并有排尿感；服3剂后，取出尿管已能自行排尿。5剂服毕，尿道通畅无阻。患者为巩固疗效，又自照原方进服5剂，共服药10剂，多年之苦疾告愈，多次追访，未见再发。\n\n","categoryId":"000dd610e12-aad4-4b47-926b-ccf8a4eefa03","publisherId":null,"applicationId":null,"type":null,"tags":null,"url":"/2011/01/4839.html"}