{"id":"000864f640a-45d3-4210-b064-8897473d77c9","created":0,"title":"烧香燃艾熏蒜 消灭恼人刺瘊","description":"　　生了刺瘊，反复多次治疗都无法祛除，有这类苦恼的患友不妨试试市民马女士提供的偏方，其原料是干的艾蒿茎、祭祀用的香以及大蒜。马女士丈夫的刺瘊就是靠这个办法成功祛除的。 　　马女士告诉记者，她丈夫年过四十，以前脚腕和脚底板处长了六七个刺瘊，大的有黄豆大小，小的有米粒大小。因为走路时鞋子会摩擦到脚上的刺瘊，非常难受，她丈夫曾多次想把刺瘊祛除。可试用了激光、冷冻等各种办法，总是治标不治本，刺瘊很快就在老位置又冒出来。走路时鞋子磨脚上的刺瘊，这种痛苦伴随了马女士的丈夫近十年。\n　　2004年，马女士偶然听朋友说了个偏方，便让丈夫照方去试。先将大蒜切片，越薄越好，最好能透光；然后取一根晾干的艾蒿，去叶留茎，将艾蒿茎与一根香并在一起点燃；一手拿薄蒜片，放在刺瘊上方，另一手拿点燃的香和艾蒿茎，对着蒜片熏蒸刺瘊，距离以蒜片不碰刺瘊、皮肤不感到过热为准；待薄蒜片熏得发干时，更换蒜片继续熏。\n　　马女士说，她丈夫知道这个偏方后，没事就熏脚腕上那个最大的刺瘊，一天熏四五次，每次熏五六分钟。三四天后，他发现这个黄豆大小的刺瘊开始发干；继续熏蒸了几天，刺瘊就扁塌下去；持续半个多月后，这个最大的刺瘊逐渐干瘪、自行脱落了。大刺瘊脱落后，马女士丈夫脚底板上的其他几个小刺瘊也在不知不觉间脱落不见了。\n　　从那至今，马女士丈夫的脚上再也没有长过刺瘊。马女士说：“这个办法原料安全，祛除后不复发，效果比激光、冷冻等方法好多了，快让患友们试试吧。” \n","categoryId":"000938e4eb3-6450-4147-b625-62b4ccc00586","publisherId":null,"applicationId":null,"type":null,"tags":null,"url":"/2013/07/9424.html"}