{"id":"000e25a07c9-eb80-46d6-ad3f-0a9cd7d58dc4","created":0,"title":"黄水疮偏方-读者献方","description":"黄水疮偏方\n　　电话尾号2917的读者献方\n　　 偏方：松香、香油\n　　 用法：在药店里，买一些松香。然后，将其擀成面，与香油搅在一起。用此物，往黄水疮部位抹。一天抹两次，一次50分钟。半个月内，此病就能治愈。\n\n　　偏方来历：\n　　近日，家住红岗区的黄女士打来电话说，她有一个治小孩黄水疮的偏方，很好使，想推荐给读者。\n　　据黄女士讲，她十一二岁的时候，有一天早晨起来，觉得下巴上有点儿痒，用手一挠，觉得有些不对劲儿，对着镜子一看，原来是起了一个黄水疱，她急忙把这事告诉了妈妈。妈妈仔细看过之后，说是黄水疮，一再嘱咐她不能用手挠，因为黄水流到哪儿，哪儿就会接着长。\n　　没想到，她妈妈的话还真说中了。第二天早晨起来，黄女士发现自己的嘴边又起了好几个水疱。\n　　这一次，她没敢再用手去挠，可疮面仍然在不断扩大，这可急坏了她妈妈。当天下午她放学回到家中，她妈妈催她快些吃饭，然后好上药。\n　　吃过晚饭，黄女士的妈妈拿了一块黄色透明的东西，又拿来蜡烛和一只装着凉水的碗。她妈妈把蜡烛点燃后，又用小镊子把那个黄色透明的东西夹起来放到火上去烧，慢慢地，那黄色的东西被烧化滴到凉水碗里，然后她妈妈将蜡烛吹灭，把刚刚滴到凉水碗里的黄色东西取出来，碾成细面，又取来香油，和那细面一起调成糊，涂到黄水疱上。直到晚上睡觉前，她妈妈也没让她洗掉。\n\n　　第二天早晨起来，黄女士洗掉了脸上的糊，一照镜子，发现黄水疱已经开始变干。\n　　当天晚饭后，她妈妈又给她糊了一次。\n\n共2页    1 2 下一页 尾页\n\n　　三四天后，干巴的黄水疱自己脱落了，只留一点红印。没过多久，就全好了。\n　　最后，黄女士还详细地介绍了她使用的那个小偏方的做法：\n　　将松香点燃，把烧化的松香滴入事先备好的冷水碗里，再把滴到碗里的松香收集起来，碾碎，用香油调成糊，涂到患处。\n\n　　连续涂1-3天，黄水疮就会自行结痂。停药后几天，结痂就会自然脱落，不会留疤痕。\n共2页   首页 上一页 1 2","categoryId":"000938e4eb3-6450-4147-b625-62b4ccc00586","publisherId":null,"applicationId":null,"type":null,"tags":null,"url":"/2012/12/8471.html"}