{"id":"000ac7faa06-730d-44c3-bb66-caca5d1e931d","created":0,"title":"儿童湿疹特效方","description":"儿童湿疹是常见病。记得为女儿湿疹跑过两次儿研所，第一次看到女儿脸上，手上，耳朵上出象癣一样的皮屑，圆圆的一块一块，紧张的要命。到儿研所皮肤科就诊，等了两个多小时，医生看病时，特别轻描淡写地说，哦，是干性湿疹。开了肤乐霜两支。我想咨询原因，简单一句，原因不明。没有两分钟，不容我多问，就让下一个病人来就诊了。第二次就诊情形也差不多。肤乐霜还真管用，一涂上，女儿湿疹马上就好了，但不涂湿疹老犯，最后女儿湿疹变成了主要烂耳根。老师告诉我一个小偏方，治小儿湿疹，特效，基本就不用肤乐霜了。方子非常简单：抓一把薏米、一把红豆（或称赤小豆），煮开30分钟，让女儿喝汤，能吃豆更好。\n结果女儿红豆薏米汤对女儿的湿疹是特效，女儿一喝，一两天湿疹就全部消失了。大家要注意，小孩喝完红豆薏米汤，利尿，小孩会30分钟左右尿一泡尿，会尿3-4次，小心小的孩子别尿裤子。这个小方，让我知道中医的高明，简单的红豆薏米比西医的外用激素还要灵。激素抑制湿疹出来，红豆薏米祛湿，让孩子将体内的湿气尿出去，都可以达到治疗湿疹的作用。但激素有副作用，不能长期用，红豆薏米是食品，就没有这种担忧了。但红豆薏米汤是治标的药物，不能保证小儿湿疹的复发。要治本，只有健脾，因为脾是运化水湿的脏器，小儿脾脏的功能强大了，水湿能够正常代谢了，自然就不会出湿疹了。\n","categoryId":"000938e4eb3-6450-4147-b625-62b4ccc00586","publisherId":null,"applicationId":null,"type":null,"tags":null,"url":"/2009/06/808.html"}