{"id":"000d262e402-303b-4079-8e9d-79439c43451d","created":0,"title":"大蒜泥偏方治疗神经性皮炎","description":"神经性皮炎是一种常见的皮肤病，多发于青壮年，患者皮肤会突然产生阵发性的瘙痒，抓挠后出现成片圆形或多角形的丘疹。神经性皮炎是一种慢性病，病情时轻时重，容易复发，患者应禁食辛辣刺激性食物，保持平和的心态，避免过度的紧张和焦虑。中华秘方网整理了三个治疗神经性皮炎的偏方，均有成功治愈的案例。\n\n一、大蒜泥偏方治疗神经性皮炎山东济南市槐荫区的张益亭五年前患上神经性皮炎，发作时刺痒无比。患病的几年来也没有停止过治疗，很多方法都尝试过，总是治标不治本，用药后症状消失但不久后又会复发，为此非常烦恼。后来在《晚晴报》上看见一用大蒜泥治疗神经性皮炎的偏方，照着上面的方法使用后，效果明显，到现在也没有复发。使用方法：取几个大蒜去皮捣成蒜泥，将捣好的蒜泥均匀涂抹在患病处，十分钟后冲洗干净，一天使用一次，一般三到五天即可见效。\n\n二、艾韭椒偏方治疗神经性皮炎山东省招远县的王亭患有神经性皮炎二十多年，一直没有治愈，发作时其痒无比，常常抓破皮肤。后来同村一友人介绍了一个艾韭椒治疗神经性皮炎的偏方，用药后症状消失，一直没有复发。配方：花椒（50g）、艾蒿（200g）、韭菜（200g）。使用用法：把上述材料用水煎煮，煮沸后取汁液备用。每天使用前将药液稍稍加热后清洗患处，一天清洗2次，一般三剂药即可见效。三、醋蛋液偏方治疗神经性皮炎河南郑州的离休干部晃钟鸣几年前脖子上生出了一片小疙瘩，奇痒无比，而且反复发作。\n去医院就诊后得知是患了神经性皮炎，治疗多次也没有治愈。\n后来尝试着用醋蛋液涂抹患处，每天涂抹三次，使用一个星期后，患处开始出现蜕皮，也不再痒了，困扰多年的神经性皮炎竟然治愈了。\n","categoryId":"000938e4eb3-6450-4147-b625-62b4ccc00586","publisherId":null,"applicationId":null,"type":null,"tags":null,"url":"/2017/12/16487.html"}