{"id":"000d82b55c0-7ef5-4d34-ba61-c054d3ae9592","created":0,"title":"分享个白发变黑偏方","description":"分享个白发变黑偏方！\n　　我表弟以前“少白头”，初中的时候就有一半头发是白的。后来几年没见，重新见他的时候，发现头发基本全黑了。我跟他说不要染发，染发剂对皮肤不好，有各种副作用。他说他没染发，是头发重新长黑了。我当时很诧异，问他怎么做到的。他说以前在某医院做保安的时候，跟一个老中医关系很好，那人给他推荐了一个偏方。我让他抄给我了，虽然我头发都是黑的，但是我相信很多人有白发的困扰。　　今天看了那个分享偏方治头皮屑和头皮痒的帖子，我突然想到我这里也有一个可以分享的。　　现在公布如下：　　红葡萄酒2kg（如果红酒不够用可以继续添加），旱莲草100g，黑豆100g，熟地100g，野生何首乌100g（何首乌一定要用野生的）中药买回来用水清洗一下。用玻璃容器泡制一周后便可以饮用，早晚各一次，一次100g。\n　　谁的白头发如果因此变的乌黑了，记得顶一下帖子。如果谁有其他偏方，也可以在跟帖里分享一下！\n　　供方：大勃若痿 \n","categoryId":"000938e4eb3-6450-4147-b625-62b4ccc00586","publisherId":null,"applicationId":null,"type":null,"tags":null,"url":"/2014/09/11346.html"}