{"id":"0001f59d5db-2bed-4845-abe6-4e48cdcae29a","created":0,"title":"蜈蚣咬急救","description":"蜈蚣咬急救\n１．症状∶蜈蚣系多足类之节足动物；腹黄形扁，长约三四寸。腮脚钩端具有毒腺，蛰人时能将毒液注入伤口内部。与北方蝎子同为五毒之一。常栖息於朽木石隙或潮湿之处。足部被蛰，则剧痛红肿，由踝、烃、肿至膝上。若不速治，毒攻心脏即死。\n２．治法∶\n第一方∶捕捉雄鸡一苹，足上头下，以倒立之。其口内涎液自然流出。尽速将涎液涂於伤口及红肿之处，痛止肿消，神效立奏，匪夷所思，如嫌涎液不足，鸡口抹入食盐少许，涎必源源喷涌，纵同时多人被蛰，其涎量亦足敷应急也。\n第二方∶用食盐两撮或两匙，无论粗盐晶盐皆可，以温水或凉水箸搅溶化，速涂或泡入伤口及红肿之处，三五分钟，断断痛止肿消而痊。 \n３、说明∶\n第一方∶愚家乡江西瑞金一带民间习用之单一方也。犹忆幼时小朋友某，突被蜈蚣蛰伤，猛投母怀痛哭，其母便用此方治之，当即痛止肿消而愈。愚实目睹亲历，非敢向壁虚构也。\n第二方∶道友伍伯高先生实证之单方也。某岁伍任职私立自由中学，一日清晨，训导主任廖敌迪先生腹泻如厕，忽忽纳履，石足犬趾突剧痛倘血，顷刻，申趾而踝，红肿浸及膝下。时校址设於桃园龟山，荒山岑寂，急救无由，廖随手缀碘酒涂之，非特不能止痛，且右足黑、肿，状如陈死人之足。伍早起邂逅，得悉缘由，奋勇检阅夙藏之方书，以为选用此方最妙，乃立取晶盐两撮，温水牛盆，箸搅溶化，并促使被蜇之右足泡水，不意才经三、五分钟，竟痛止肿消而愈矣。惟用水调盐，不可太淡；须达普通酱油之咸度，方有杀菌解毒之效能。伍再三叮咛，不可不知，故备述之。既而璁假居临，有赣籍事务员某君，夜间贪凉，席地而卧，正酣睡间，忽然眼之周际剧痛，睁眼辄睹长约五六寸之蜈蚣，逝洒而窜。既尝闻廖主任被蜇急救之方，亦拟用水调盐以解。而是夕适值停水，一时情急智生，觅盐一勺，但凭口液嚼化，合眼敷伤，蒙陇入睡，翌日晨日上三竿，一醒即肿消而瘥，若无其事然；而眼际盐霜，则凝如薄饼云。\n（李乐俅居士贡方．台湾） \n","categoryId":"000938e4eb3-6450-4147-b625-62b4ccc00586","publisherId":null,"applicationId":null,"type":null,"tags":null,"url":"/2009/06/493.html"}