{"id":"0006bb05158-bc20-432e-b8e0-8521f7abfcde","created":0,"title":"制霉菌素片对付鹅口疮","description":"制霉菌素片对付鹅口疮\n　　上周，涧西区陈女士给本刊打来电话，她女儿5个月大时嘴里出了鹅口疮，一直到现在都没有好。用了很多药都不能彻底治愈，想寻找一个治疗鹅口疮的方法。\n　　涧西区张女士说，她的孩子在5个月大的时候也患了鹅口疮，当时她急得不行，抱着孩子四处看病。外用的药膏给孩子用了很多，病情就是得不到缓解。一个医生告诉张女士，把制霉菌素片压碎碾成粉末，用药用棉棒沾药粉涂抹患处，一个患处只能用一个棉棒，棉棒不能反复使用，否则就会交叉感染，孩子的病情也会久治不愈。\n　　张女士按此方法给孩子涂抹了几次，果然十分有效，两天后病情就有所好转。母乳喂养的孩子，也要在妈妈的乳头上涂抹制霉菌素片药粉。如果是奶粉喂养的孩子，要把奶嘴和奶瓶用开水煮，彻底消毒。\n\n","categoryId":"000938e4eb3-6450-4147-b625-62b4ccc00586","publisherId":null,"applicationId":null,"type":null,"tags":null,"url":"/2013/08/9847.html"}