{"id":"0003822ab0e-e513-4a59-896b-8fff1917fc94","created":0,"title":"黄甘油抹好牛皮癣","description":" 网友（云~物流）提供：       她邻居一位大姐，患牛皮癣多年，到处求医花了很多钱没有治好，后来打听到一偏方，用黄甘油抹好了，这位辽宁的热心网友把那位大姐的电话告诉我，打通电话后我向那位大姐具体咨询了这个方子，她说用黄甘油抹了一个多月就好了，以前她是全身性的，而且还有裂口特别疼痛，可遭罪了，大小医院都去了，花费二三万都没有治好。\n      朋友提供这一偏方解决了难题，希望能推荐给同病者使用，让他们也早日得到康复！（提醒：黄甘油就是修车用的黄油，要到正规汽修配件店买）此方虽然不可思议，但确实管用，而且没有副作用，如果久治不愈，可以尝试下，起码多了一次治愈的机会！也希望各位医者不要乱加批评无科学依据，毕竟供方者也是一片热心，希望尊重！谢谢       （提供者：霍大姐 ）\n","categoryId":"000938e4eb3-6450-4147-b625-62b4ccc00586","publisherId":null,"applicationId":null,"type":null,"tags":null,"url":"/2012/04/6260.html"}