{"id":"000d63b015a-32e2-4a8e-89e4-e28358245d70","created":0,"title":"乳腺增生的一个中药方！","description":"       告诉大家一个乳腺增生的中药方，据说此方很管用，曾经吃好过6个人，效果挺好！这个方子早已给我提供了，由于偏方较多，没有来得及整理，把它遗忘在角落里，今天趁着休息把此方整理下，发表出来供女性朋友参考，大家可以一起参考下！             治乳腺增生偏方：荔枝核20克，山楂核15克，橘核20克，赤芍15克，香附15克，青皮15克，川芎12克，丝瓜络30克，每天一剂水煎服，至少吃10付药看效果。\n      此方很多乳腺增生患者服用过，疗效很好，希望转给更多患者用！同时呼吁朋友们，如果您有使用过的好方子，不妨拿出来供患者参考，在这里互相交流，共同进步、共同健康！！也希望大家反馈使用效果，谢谢！！ \n","categoryId":"00065ead041-cd67-4b90-88b0-bbc343de0584","publisherId":null,"applicationId":null,"type":null,"tags":null,"url":"/2012/03/6105.html"}