{"id":"000fcb196c5-b8e4-4bc8-ae28-1b98b8d5e76f","created":0,"title":"米醋白酒击退荨麻疹","description":"　　被荨麻疹困扰的朋友，不妨试试米醋和白酒，或许您的苦恼就会像涧西区柳先生一样，一扫而光了。\n　　柳先生今年47岁，从3年前开始，就经常被荨麻疹困扰。有时候稍微见点凉，他的手臂或者小腿上就干燥、瘙痒，并且起一个个疙瘩。他忍不住抓挠后，疙瘩就连成片，呈一道一道的印，面积迅速扩大。医生说这是荨麻疹，民间管这叫“抓疙瘩”，吃药打针钱没少花，却没什么疗效。\n　　2008年秋天，柳先生的双腿又起了成片的疙瘩，瘙痒难耐。邻居家的一位老太太知道后，告诉了他一个对付荨麻疹的偏方：将米醋和50度以上的白酒以2：1的比例混合，涂搽皮肤患处。\n　　柳先生“照方”制成酒醋汁，用医用棉签蘸着在患处反复涂搽。柳先生说，刚涂上去时，皮肤就感觉凉凉的，原来急躁的情绪也逐渐缓和下来。涂上几分钟后，就能看到明显效果，瘙痒和疙瘩逐渐减退。十几分钟后，身上成片的“抓疙瘩”就基本不见了。\n　　柳先生说，这个办法原料易得，经济实惠，比吃药打针有效多了，有同样苦恼的患友不妨试试。\n","categoryId":"000938e4eb3-6450-4147-b625-62b4ccc00586","publisherId":null,"applicationId":null,"type":null,"tags":null,"url":"/2013/07/9527.html"}