{"id":"000f64eed3b-2993-490a-a579-f6206d53b263","created":0,"title":"烧烫伤、刀伤--通用方！","description":"烧烫伤、刀伤——通用方！\n    热心网友（我的莲花为你开 QQ317213917）：胡老师，这两天在您空间转了很多偏方，真心地说一声谢谢！我也告诉你一个比云南白药还好使的刀伤药配方吧，对烧烫伤也管用。\n    这是我最好的一个朋友家的秘方，我没经他同意就告诉您啦！这个方子是我秘藏了二十多年的，现在把它说出来，利益众生吧！我朋友在东北开药店，刀伤药和胃药是他家的招牌。胃药他没告诉我，这个刀伤药我老是管他要，我在威海，他嫌不方便邮寄，就把方子告诉我，让我自己配。这个方子是我和很多人亲身验证过的。\n    配方：冰片一两，法半夏半两，银珠半两，一起研成细面儿(越细越好)，用玻璃瓶封好，放多少年都不失效。伤口见血把药撒上去，两分钟止疼，不会化脓，迅速结痂。烧烫伤，可用香油调药粉抹上去，效果咋样，用过就知道了。此药不能用于疮疖疔毒的封伤口用，容易把毒封里面。刀伤药有个好处，都是中药，过很多年都不失效，我家现在用的还是十多年前我配制的。\n    注意：大家一定要注意，方中的法半夏就是熟半夏，药店有售，去买时一定要说清楚是要熟半夏，不能要生半夏，生半夏配出来的药会有毒，切记切记！烧烫伤起泡的话把泡挑破把死皮去掉，小的伤直接撒药封上就行。大的伤要把药用纯香油调稀后再抹上，否则结痂太硬拉的人的皮肤太紧，会不舒服。把这三味药一定要磨得像面粉那么细，混匀了，用容器封好，要防潮，冰片易挥发。\n    您利益众生的善举着实令人感动，阿弥陀佛！\n    献方人：焉镜勇老师\n \n    后附：自昨日发表我的偏方以来，一天的时间加我为好友的请求如雪而至。大家都不太明白银珠是什么，银珠是一种红色的粉末，中药店或中医院有售，大家可以咨询当地的中医。本人很忙，不能每个人都一一解释一遍，敬请见谅。\n","categoryId":"000938e4eb3-6450-4147-b625-62b4ccc00586","publisherId":null,"applicationId":null,"type":null,"tags":null,"url":"/2014/10/11392.html"}