{"id":"0007cebd1f0-45d1-4cb1-b292-c2996db44519","created":0,"title":"香蕉皮“护手霜”防治冻疮","description":"香蕉皮“护手霜”防治冻疮\n 　　冬季，不少人会受冻疮困扰，市民马先生提供了一个偏方：用烤热的香蕉皮当“护手霜”。\n　　马先生今年40多岁，从小手上就经常出现冻疮。几乎每年冬天，他的双手都肿的像胡萝卜似的，红肿的皮肤下有脓液，非常难受。当兵时，部队的一个老班长给他说了这个偏方。于是，当年刚过秋天，马先生就买来了香蕉，剥一只，把香蕉皮靠瓤的一面对着火烤约两分钟，待发热后就用其在手背、手指上反复搓揉。马先生只用了两次，那年手就没再冻过。\n　　后来，每到秋冬季节，马先生吃香蕉时就会使用这个方法，一来是预防冻疮，二来香蕉皮含有维生素和矿物质，用发热的香蕉皮搓手还能滋润皮肤。马先生说，这个方法用来防治冻疮最好，老少皆宜。对于爱美的女孩们来说，这种香蕉皮“护手霜”对手部皮肤的保养效果也很不错。\n","categoryId":"000938e4eb3-6450-4147-b625-62b4ccc00586","publisherId":null,"applicationId":null,"type":null,"tags":null,"url":"/2013/07/9611.html"}