{"id":"0005d112c99-785d-422e-adc1-58c220af6a7f","created":0,"title":"麝香塞耳治三叉神经痛有效率100％","description":"麝香塞耳治三叉神经痛有效率100％ \n方法：麝香少许，用绵纸包裹塞入耳孔内（哪边疼塞那边）。\n验例：平顶山13矿王明同志20年前患三叉神经痛，多方医治无效，用其方其痛立止，至今已十余载未复发。\n荐方人：河南栾川县赤土店镇赤土店村---尤永杰。\n山西太原市北城区迎新街道办事处杨建政用此方治愈了孙女爱萍的三叉神经痛，艳萍患病7个月，疼的不能睡，饭不想吃，痛起来大哭。用此方后现在完全止痛痊愈了。\n黑龙江齐齐哈尔药材采购供应站南马路1号李琴用此方治好了他亲属多年的三叉神经痛。\n董氏中医用此方法给30例三叉神经痛试用，有效率在100/100.治愈率在90/100以上.\n","categoryId":"00019398938-d600-4efc-b0ad-f185419273f2","publisherId":null,"applicationId":null,"type":null,"tags":null,"url":"/2013/03/8684.html"}