{"id":"00097339dad-d2b1-4bdf-9bc2-90ccc2e33eb0","created":0,"title":"喝下半身不遂酒，高度致残能行走","description":"喝下半身不遂酒，高度致残能行走配方：生川乌，生草乌，各15克，蜜炙双花，豨莶草，忍冬藤，各30克，蜈蚣3条，全蝎5条。用法：以上七味装入坛内，加入3斤白酒，将坛放入锅内加水至半腰深，盖锅盖，烧开后用文火炖1个小时，即可。服法：药渣一直泡在酒内，每服一两，一日三次，饭后服。酒量小可适当少服。疗效：一般服完一料药酒，即可痊愈。案例：石xx,男，56岁，患半身不遂，生活不能自理，本地大夫用药治疗疗效不明显，后经用此方，疗效明显，手脚灵活像个正常人一样。喝了半身不遂酒，像正常人一样走，花钱不是特别多，穷人不用很发愁。 \n","categoryId":"00019398938-d600-4efc-b0ad-f185419273f2","publisherId":null,"applicationId":null,"type":null,"tags":null,"url":"/2013/06/9113.html"}