{"id":"000ae9d2385-e817-450d-b53d-5e437f525bbc","created":0,"title":"现身说法：一个偏方治好了丈夫的腰肌劳损！","description":"      网友：尘封记忆 说自己有个治疗腰肌劳损的偏方想提供给大家，希望能帮助更多的人走出困境。因为她深知此病的痛苦，后来一个偏方给了丈夫希望，20付中药就治愈了。下面把方子发表出来，一是给腰肌劳损患者一次治愈的机会，二来也是让这位热心朋友在网站体现自身的价值！\n \n      处方：杜仲10克、续断10克、生地10克、赤芍10克、当归10克、桃仁10克、鲜生姜10克、肉桂6克、乌药6克、威灵仙6克。每日一剂，水煎服。上方一般服药1-10剂，即可得到明显的效果，20剂大多数可根治。\n     本方对肾虚腰痛、风湿腰痛、淋证腰痛、瘀血腰痛也有一定的疗效。\n \n     （再次感谢：尘封记忆 这位无私奉献的热心朋友，祝愿您和家人都能得到老天的照顾，身体健康、万事如意！感谢您的奉献） \n","categoryId":"000124c1a30-8944-4d43-b46c-97fdd7ee6a86","publisherId":null,"applicationId":null,"type":null,"tags":null,"url":"/2012/04/6406.html"}