{"id":"000ebf0cf02-baf8-42d6-9166-94602dc51760","created":0,"title":"足根痛偏方(适用炎症引起的足跟痛)-王女士献方","description":"足根痛偏方(适用炎症引起的足跟痛)\n　　求方回音上期，读者姜女士，给记者打来电话，询问足根痛偏方。姜女士，到海南买房子，天天看楼盘。道走多了，得上了足根痛。她从海南，给记者打来求方电话。求方信息一登出，招来不少献方人。其中，新村的王女士，方子挺简单，治疗效果还挺好。记者将此方子以短信形式，告诉了姜女士。本期，记者将此方登出，供其他患者使用。　　王女士献方处方：仙人掌用法：取一片脚后跟大小的仙人掌，将两面的刺拔掉。然后，再将一面的绿皮片掉。片好后，将露瓤的部分，敷在疼痛的足根上。再用保鲜膜，进行包裹封闭。外面，再用布将其缠上。每天，敷12个小时。一个星期内，只要是炎症引起的足根痛，就能治愈。　　治疗病例王女士，家住乘风庄，今年63岁。20年前，她被确诊为糖尿病。这些年来，她一直跟糖尿病作斗争。每天晚上，她都坚持进行体育锻炼。其实，她的锻炼，也很简单，就是走步。晚饭后，她得围着楼区，走个十圈八圈的。糖尿病，还真是个欺软怕硬的“手”。王女士，体质增强了，糖尿病症状，也越来越轻了。去年的时候，她又增加了运动量。她把走步的圈数，翻了个倍。刚走了一天，她就感觉不对劲了。突然感觉，右脚后跟，钻心的疼。只要是一走道，脚跟就不敢着地。这种情况，她以前也有过。疼的时候，吃几天消炎药就好了。这回，她连吃了12天的消炎药，可脚后跟，还是疼得难受，一点没见好。多日不见王女士来锻炼，平时跟她一起锻炼的同伴，着急了。\n\n共3页    1 2 3 下一页 尾页\n\n一个同伴，给她打电话，问她咋地了？王女士，把脚后跟疼的事，告诉了同伴。同伴一听，急够呛。她对王女士说：“你咋不早说呢，我有个偏方，治足跟痛贼好使。”随后，她让王女士等着，就挂断了电话。不大会儿功夫，同伴带着一袋子仙人掌，敲开了王女士家的门。进门，她就走进厨房，用刀拔仙人掌的刺。然后，她把一面的绿皮片掉，露出仙人掌黏性的一面。她把仙人掌黏性的一面，敷在王女士右脚根上，用保鲜膜封闭后，再用布进行了包扎。整完这一套后，她告诉王女士，必须包12个小时，而且一天包一次。王女士说，以后的几天，她就在睡觉前包上。然后，在床上一躺，就是12个点，再把仙人掌拿掉。用了两天后，她丝毫没感觉到效果。她打电话给同伴，同伴说，让她坚持。结果，她用到第四天时，见效了，脚后跟疼痛减轻了。包到第五天时，脚后跟彻底不疼了，咋跑咋跳都没事了。后来，王女将这个方子，又告诉了四个人使用。其中三个人，都治好了足根疼，只有一个人没治好。王女士还挺纳闷，为啥那个人的足跟痛没治好。最后，她才明白。没治好的那个人，是骨刺引起的足根痛。其他的人，是炎症引起的足跟痛。所以，这个方子，只适用炎症引起的足根痛。\n\n共3页   首页 上一页 1 2 3 下一页 尾页\n\n　　药理分析仙人掌，不同于芦荟，它的全株，均可入药。但仙人掌的刺内，含有小毒，一般不用。仙人掌，可清热解毒、散淤消肿。民间，如果长了疙瘩、疥子，一般把仙人掌的汁抹上，几天就好。如果嘴上起泡，上火了，也可以吃点或抹点仙人掌的汁，几天就见效。正因为仙人掌有消炎功效，所以用其外敷，使其慢慢渗入皮内，就能治愈肉内炎症。所以，此方治疗炎症引起的足跟痛，有科学依据。　　温馨提示拔仙人掌的刺时，一定要注意。这东西，内含毒汁，人体被刺后，容易引起皮肤红肿疼痛、瘙痒等过敏症状。使用过程中，一定要用保鲜膜包严。否则，仙人掌的黏液，容易干掉，影响治疗效果。\n共3页   首页 上一页 1 2 3","categoryId":"000124c1a30-8944-4d43-b46c-97fdd7ee6a86","publisherId":null,"applicationId":null,"type":null,"tags":null,"url":"/2012/12/8318.html"}