{"id":"0009bfa5f38-0c79-40f2-b419-e69da301cfc6","created":0,"title":"偏方治好网球肘！","description":"    我也说一个治疗网球肘病的偏方：前几年因搬重东西伤了左胳膊肘，整天酸痛，影响睡眠，到医院检查说是网球肘，没什么好办法，痛得厉害就打封闭。后来在《生活中来》看到一个偏方，启用后治好了，至今未犯。\n    此方：蓖麻籽7粒，去掉外皮；刺菜（扎扎菜、大蓟，华北地区地里都长此野菜）一小把，茎叶都可用，越鲜嫩越好，洗净晾干后切碎，找一容器，把蓖麻籽和刺菜放到一起砸成糊状放到玻璃瓶里备用。每次取一小汤勺平涂在受伤胳膊弯曲处，用薄塑料袋单层缠两圈，再用纱布包好，两天换一次，半月即可见效或痊愈，有时感到痒或出现红疥头属正常现象，说明是有效果的症状。\n    无副作用，不妨试一试。用完再按此比例制作，一直到痊愈。\n    献方人：韩孟雨（祖籍河北省，现住北京）\n\n\n","categoryId":"000124c1a30-8944-4d43-b46c-97fdd7ee6a86","publisherId":null,"applicationId":null,"type":null,"tags":null,"url":"/2012/08/7195.html"}