{"id":"0007a9a2bd5-e866-4e1c-8241-6c706376bd67","created":0,"title":"尿路感染、盐水帮办！","description":"尿路感染、盐水帮办！\n    热心网友：（上善若水 qq 943875466）“您好，我有一治疗尿路感染的偏方，简单易行且效果很好，已有很多患者用过，这个方法就是：在感染期喝一碗淡盐水（最好在早晨空腹喝，记得是淡盐水，也就是在一杯水里放一点盐就行），我九十多岁的老父亲，去年因肾积水，插尿管，引起感染，在医院久治不愈，就是在喝了一碗淡盐水后而愈。就这么简单，有此症的朋友，不妨一试。（希望您转一下，想让更多人受益，给您添麻烦了，阿弥陀佛！）这是邻居大妈告诉的，说是她们老家的一个乡村医生给说的，她自己用过的，很好。后来我给两个人提供过，都很好，没有任何副作用，请放心使用。”\n    献方人：刘慧艳老师 （山东阳谷）  \n","categoryId":"000dd610e12-aad4-4b47-926b-ccf8a4eefa03","publisherId":null,"applicationId":null,"type":null,"tags":null,"url":"/2013/09/9992.html"}