{"id":"0006770db1a-e90e-4645-a2a9-6bb0b47b443e","created":0,"title":"本秘方治肾炎蛋白尿一般15天可消失","description":"配方及用法：黄毛耳草30克，丹参20克，贯众、萆薢各10克，甘草3克。有明显尿路感染症状者加蒲公英25克，尿血明显者加大蓟、茅根各10克。水煎服，每日1剂，分2次服。\n禁忌：忌高蛋白、高脂肪饮食。\n注意：临床症状消失后，尿检正常，乳糜尿试验阴性，仍需服7~10天后才能停服。\n\n疗效：一般治疗15天后，尿蛋白消失，乳糜尿转阴性。\n荐方人：江西抚州地区 何贤榕\n【小知识】\n什么是蛋白尿(蛋白尿)？正常人尿液中有无蛋白？\n蛋白尿(蛋白尿)是尿液通过酸化加热后混浊而检出的。正常人每天尿中排出的蛋白质一般为40～80毫克，上限为150毫克，称为生理性蛋白尿。由于量少，常规化验检测为阴性，超过150毫克/日，即属于异常蛋白尿。人体在剧烈运动、重体力劳动、情绪激动、过冷、过热及在应激状态时，蛋白尿-尿蛋白的排出量均可增多，称一过性蛋白尿，在几小时或数天后即可恢复正常。\n","categoryId":"000dd610e12-aad4-4b47-926b-ccf8a4eefa03","publisherId":null,"applicationId":null,"type":null,"tags":null,"url":"/2017/08/16335.html"}