{"id":"000b67fb4f6-cb2d-4c85-a220-af75d9da694c","created":0,"title":"长在手上的脚气更让人担心！","description":"长在手上的脚气更让人担心！郑先生和朋友一起吃饭时，不停地放下筷子，双手合十反复揉搓，朋友不解，轻声问他，郑先生显得很无奈地说，手经常脱皮，已经是今年第4次了，用药抹了也一直不好，又痒又痛，很难受。朋友建议他到医院皮肤科做检查，结果让郑先生大吃一惊，原来他手部脱皮竟是因为脚气经久不愈感染所致。夏秋季常见手足癣中药外洗效果佳脚气若不及时治疗，易传染至其他部位，如手等。河南中医学院第一附属医院皮肤科主任医师常贵祥介绍，治愈足癣是完全有可能的，因为现在抗真菌药物完全可以杀灭附着在脚上的真菌。根据郑先生原来的用药情况得知，他没有一种药坚持使用过，往往是症状一有缓解就停止用药，有了症状再用。如此反复，原来有效的药物也变得无效了。对于没有脚气的人来说，平时应注意防范，如保护好脚部皮肤不受损伤，注意其干燥和透气；对于已患脚气的人来说，在治疗脚气的过程中，切勿觉得症状减轻或没了脚气就自动停药。一般患者自觉好得差不多，其实是真菌“潜伏”起来了，只有通过最少1～2个月的持续治疗，才能保证脚气的根治。无论是足癣还是手癣，都应及时治疗，可用达克宁、布替奈芬乳膏等进行外涂。而对于夏秋季比较常见的糜烂浸渍型手足癣，用中药进行外洗效果非常好。有一个小验方，大家不妨一试：取黄柏、苦参、白鲜皮、艾叶、石榴皮各15克，花椒10克，加水适量，大火煮沸后改用小火煮20～30分钟即可，每天用药汁清洗或浸泡局部，1剂药可用2天。另外，如果有些人皮肤局部出现红肿、疼痛、糜烂等现象，可加上金银花15克，连翘30克，因其具有清热解毒、消肿止痛的作用。\n专家点评对抗脚气的民间秘方1.热水烫脚能杀死真菌？（错）脚气是由真菌感染引起的皮肤损害，有些人患了脚气习惯用热水烫脚，其实热水无法杀灭真菌，对缓解脚气也没有任何作用，反而容易引起更为严重的并发症。2.冰醋酸可杀死真菌？（不一定）浓度高的冰醋酸确实可以杀死真菌，但会严重伤害皮肤。一般来说，大多数皮肤科医生反对患者使用高浓度的冰醋酸来治脚气，尤其是有水疱或溃疡者。但用冰醋酸治疗脚气确有帮助，一般将30%的冰醋酸兑水，使其浓度在10%左右时用来泡脚，对脚气的治疗是最好的。3.随便买点药治脚气？（错）一旦患上脚气，应及时就医，遵医嘱规范治疗，不要觉得症状不严重而拖延，更不要自己随便买点药涂抹了事，因为脚气属于真菌性皮肤病，治疗通常需要一个周期，更需要综合治疗。一般来说，抗生素的治疗是在1周以内，但真菌感染在1周以内的治疗效果会显得相对薄弱一些，很多患者没有听从医生的处方建议，往往在用药后，症状稍微缓解就误以为已经根除，放弃治疗，从而引起疾病复发。4.绿茶治脚气？（不妨尝试）滕阿姨曾患有严重的脚气，去年她在一位朋友的建议下使用绿茶治脚气，半年后，症状竟有所缓解。现在，滕阿姨每次碰到患有脚气的朋友都介绍自己的经验。其实，做法很简单。滕阿姨说，于每晚睡前，用花椒、绿茶各10克，加水2500毫升煮开，放少量醋，待温度适宜时浸泡双脚，每次半小时，然后用干净毛巾擦干双脚。坚持每晚泡脚1次，一般1周后就会见效。滕阿姨说，绿茶可以是最便宜的那种，但越新鲜越有功效，最好是当年的新茶，不要用金属盆子装。5.风油精对抗脚气？（治标不治本）在一家私营企业上班的陈婕患有脚气，她治脚气的方法是使用风油精。具体方法是：于每天睡前用温水洗脚后，用棉签蘸适量风油精涂于患处，一般连用一个星期，就能达到止痛、止痒的功效。陈婕说，风油精治脚气只是暂时缓解，并不能达到治本的效果。脚气是真菌引起的常见皮肤病，而风油精中含有的薄荷脑、樟脑、桉叶油、丁香酚、水杨酸甲酯等成分，能够起到清凉、止痒、杀菌、抗菌的作用，因此可以暂时缓解脚气症状。需要注意的是，孕产妇、婴幼儿禁用。\n您要体会的最亲民的保健方法：泡脚泡脚有益，从清水到药浴，泡脚也越来越讲究了，如超市里非常流行的足盐，盐水浴的原理其实和在海水里泡几次的道理是一样的，盐水浴能除湿杀菌、解毒凉血、镇痛止痒，常用于治疗皮肤病和脚气。此外，在洗脚水中添加中药效果也不错。如取乌梅100克，水煎后泡脚能治疗脚气。\n \n","categoryId":"000d3e70cea-06ab-418e-9f4c-aa7eba26fb60","publisherId":null,"applicationId":null,"type":null,"tags":null,"url":"/2013/06/9019.html"}