{"id":"0008ca595d8-aefc-4139-b40a-5ecdede5fa2f","created":0,"title":"肾结石别烦恼、中药方效果好","description":" 肾结石别烦恼、中药方效果好！\n    热心网友（阿傻  QQ504700819）：胡老师你好，我想奉献一个肾结石方。\n    这个药方是我朋友的亲戚提供的，他在大医院当医生，我老妈上个月才用过，连用三剂药就排出了结石。另外我身边还有三位朋友也用过，全都排出了结石。\n    药方：金钱草30克，茯苓15克，海金沙15克，生地15克，滑石20克，石苇15克，猪苓15克，泽泻15克，生大黄10克，冬葵子15克，生地榆15克，车前子15克，鸡内金10克，莪术10克，地龙10克，赤芍10克，元胡10克。琥珀3克（汤药冲服）。\n    用法：以上为一剂，加水熬，然后用熬出的药冲服琥珀，每天一剂可以分两次服用。因为这一剂药非常多，最好用大一些的砂锅或者不锈钢锅熬。\n    希望这个药方可以帮助有需要的人！\n    献方人：唐永增老师\n","categoryId":"000a43873e6-4e3b-4f9d-bb16-7ede9b04b54b","publisherId":null,"applicationId":null,"type":null,"tags":null,"url":"/2014/12/11501.html"}