{"id":"0003ba2491a-e994-40a7-8067-0d1021a8256e","created":0,"title":"香油炸花生 胃溃疡去无踪！","description":"香油炸花生、胃溃疡去无踪！    热心网友:(青莲菩提妙智 qq:1544774903)：末学母亲的高中同学雷阿姨，上周到家里拜访，提起她多年前的老胃病，记得当时阿姨胃溃疡病疼的厉害，犯病时都是弯着腰 。最重的一次犯胃病，是同事送到医院去。请假无法上班。现在阿姨的胃溃疡痊愈了，提起她的秘方，是她的一位朋友提供的，不花一分钱，也不用煎药，就是用芝麻油炸花生米。\n    具体做法：芝麻油加热，炸熟花生米，切记任何作料不要添加。雷阿姨说，每天吃点，没有定量，三个月就好了。后来也没有犯过。她又把这个方子推荐给了三个人，都有效。希望能给患者提供点帮助！\n     献方人：褚冬婷\n","categoryId":"000a43873e6-4e3b-4f9d-bb16-7ede9b04b54b","publisherId":null,"applicationId":null,"type":null,"tags":null,"url":"/2012/11/8017.html"}