{"id":"00085460d33-08f3-483d-85c6-aeb45d4cf03b","created":0,"title":"胆囊疾病偏方","description":" 胆囊疾病偏方\n \n1.急性胆囊炎偏方（表现为湿热、发痛、厌油、恶心、便干，舌质红苔黄腻，脉弦滑等特征）\n材料：北柴胡15克、川军15克（后下）、白芍20克、枳实15克、枯黄芩20克、半夏12克、郁金20克、元胡15克\n \n2.慢性胆囊炎偏方（表现为体倦乏力、口干咽燥、头晕目涩、舌质红体瘦小、苔薄黄或无苔、脉弦细等特征）\n材料：生地12克、生首乌20克、茵陈30克、虎杖15克、生大黄10（后下）、生山楂15克、生鸡内金6克（冲）、麦芽15克、佛手12克、玫瑰花6克。有条件者加绿萼梅9克\n \n3.胆息肉偏方（适用于湿热者）\n材料：大黄炭15克、文术15克、夏枯球30克、北龙胆草15克、生山楂15克、白芍20克、生鳖甲30克（捣细醋炙）、甲珠6克（冲）、三七9克（冲）\n \n4.胆结石偏方\n材料：金钱草30克、海金沙15克、生鸡内金15克、金铃子10克、郁金15克、玉米须15克。肝胆结石再加枳壳15克、芒硝10克（后下）；有绞痛者加元胡15克\n \n用法：\n以上四个方子里的材料，均是一天的量，按中药方法熬制。一天煎三遍，早晨煎出一碗药汤服下，中午煎出一碗药汤服下，晚上再煎出一碗药汤服下。胆囊炎的方子，依病情不同，最快十一天便可以治愈。严重的，需要继续服用一段时间。胆结石和胆息肉的方子，治疗时间较长。\n最快，也要一个月时间方可见效。如有不明者请打18246840780，找献方人郑先生咨询。\n","categoryId":"000a43873e6-4e3b-4f9d-bb16-7ede9b04b54b","publisherId":null,"applicationId":null,"type":null,"tags":null,"url":"/2014/11/11435.html"}