{"id":"00036affcea-ffd8-40fa-bc5b-89981426c8f1","created":0,"title":"乙肝中药方、来自热心肠！","description":"乙肝中药方、来自热心肠！     热心网友（祥鸿 qq820106338）：你好，看到你空间这么多善心人送出自己用过的偏方，深深被感动。我也有个不错的偏方献给大家，是治疗乙肝的，那时我是大三阳，也吃过很多药没治好，后来是我妈妈的一个舅舅告诉我这方子的，他还特别交代不要给别人，给我们村里治愈了好几个人，所以我就一直收藏着。我那时喝了一个多月不到两个月就好了，现在看到那么多热心人，拿出来共享吧！现在我的肝功能一直正常。\n    方子：瓜蒌仁10克、瓜蒌壳5克、川朴9克、苍术15克、川莲3克、大腹皮9克、茵陈15克、生大王9克、田基黄15克，加水适量熬水，先大火后小火熬出汁液，越浓越好，每天饭后饮食。一天喝二到三次，当茶饮也行。第二天反复熬一次也行，但要熬久一点。这药在中药房全有，而且还不贵，我那时抓的好像是3.6元一副的。记住在服药期间不能吃牛肉、狗肉和鸡肉。只要是上火的都尽量不要吃，当时我妈老提醒我：别在外面吃牛肉，所以我一直记得。我也是希望能帮到有需要的人。\n     献方人：彭老师  \n","categoryId":"000a43873e6-4e3b-4f9d-bb16-7ede9b04b54b","publisherId":null,"applicationId":null,"type":null,"tags":null,"url":"/2013/09/9983.html"}