{"id":"00083babf13-9f9c-4611-ada8-104c278dfcf1","created":0,"title":"黑矾加鸡蛋治疗结肠炎","description":"黑矾加鸡蛋治疗结肠炎\n　　对于由结肠炎引起的长期慢性腹泻，可吃黑矾加鸡蛋进行治疗。此偏方由瀍河回族区的范金山和张虎齿提供。\n　　具体操作方法如下：\n　　1. 将鸡蛋打开一个小口，把蛋清倒出来一点儿。\n　　2. 把约6克黑矾粉倒进鸡蛋里，然后用筷子轻轻搅匀（黑矾较苦，搅匀可以减少苦味）。\n　　3. 用面糊把鸡蛋包起来，面糊适当厚一些。\n　　4. 将鸡蛋放进烤箱，当面糊烤至发黄微焦时取出，把面糊、鸡蛋全部吃掉；也可以蒸着吃，像蒸馒头一样，蒸15分钟即可。\n　　范金山介绍，连续吃3天，就会有效果，不成形的大便就会成形了。（因个人体质有差异，效果会有所不同）\n","categoryId":"000a43873e6-4e3b-4f9d-bb16-7ede9b04b54b","publisherId":null,"applicationId":null,"type":null,"tags":null,"url":"/2013/08/9893.html"}