{"id":"000ca7dc80e-68e9-4046-9091-726240384ec5","created":0,"title":"我临床应用几十年的治胃病屡治屡验的两个秘方","description":"我临床应用几十年的治胃病屡治屡验的两个秘方\n我是一名退休医师，在几十年临床实践中，摸索出专治胃病的中、西药秘方各一，屡治屡验，疗效极好。现将这两个秘方献出。\n中药方：当归、黄芪、桂枝、大枣各30克，陈皮6克，甘草20克，水煎服，每日1剂，分3次服，连服7天。\n西药方：维生素C 42片，维生素B6 42片，痢特灵21片。维生素C与维生素B6每次2片，痢特灵每次1片，每日3次，7天服完。\n注：中药汤剂须在饭前服，西药须在饭后服。\n百姓验证：吉林长白山县财政局陈敏，女，42岁。她来信说：“本县小学生张丽患胃疼2年多，曾多方医治效果不佳，用去医药费2000多元，后诊断为慢性胃炎、胃寒性疼痛。我用本条偏方仅1周为她治愈此病，才花药费30多元。”\n荐方人：陕西省平利县凤凰乡退休老中医 吴清明\n","categoryId":"000a43873e6-4e3b-4f9d-bb16-7ede9b04b54b","publisherId":null,"applicationId":null,"type":null,"tags":null,"url":"/2015/12/12381.html"}