{"id":"000724752ca-adeb-4d46-889f-be838616b41f","created":0,"title":"肝硬化、肝腹水偏方同时收集来的，已经有人治好了！","description":"       一位山东青岛的朋友前两天给我打电话，要给我提供一个治疗肝硬化和肝腹水的偏方，据她说治好了家乡几个人了，特别好用。当时我在上班，所以就没有详细记录。昨天晚上我们在网上进行了交流，她把这两个方子和盘托出，希望能帮助更多的患者换回新生！我很感激这位朋友，那么无私的奉献精神，值得大家学习！聊天记录就不发表了，因为大家是比较信任我的，再发显的有些啰嗦。下面言归正传，把这两个偏方公开如下，这可不是从网上或者书上直接拿来的哦，是提供者身边验证过的，切实可行的方子，希望大家珍惜，多多转发，或许您一个转发会挽救一个危在旦夕的生命、会给一个家庭带来希望！\n       1、肝硬化偏方：野兔加红小豆，不见盐，不见铁，最低吃三个。用砂锅煮最好，千万不能沾铁锅。野兔肚子里塞满红小豆。\n       2、肝腹水偏方：河廖子煮瘦肉吃，但必须是叶子中间有个黑点的那种，中药店也有售。不用盐，不见铁，坚持吃一段时间就能好。\n       （热心网友：一剪寒梅 qq1136769844 提供）  \n","categoryId":"000a43873e6-4e3b-4f9d-bb16-7ede9b04b54b","publisherId":null,"applicationId":null,"type":null,"tags":null,"url":"/2012/04/6386.html"}