{"id":"000ab857229-5e3a-474a-ac9d-3035139159ee","created":0,"title":"多年的痔疮用地锦草大蒜辫煮水熏治愈","description":"我患痔疮多年，严重时大便血流不止，虽用过一些药物，但疗效甚微。偶然的机会，朋友介绍一则偏方，仅治疗2次，现已痊愈。此秘方经一些患者使用，亦收到良好效果。\n配方及用法：地锦草干品20克或鲜品200克，加大蒜辫一个，放在盆内加水没过草药，煮沸10分钟后，用热气熏患处，待药液变温后用其洗患处。下次使用时将药液加热，方法如前。每日早晚各熏洗1次，连续使用3~5天，即可收到明显疗效。\n注：大蒜辫即弃掉蒜头用大蒜茎、叶编成的辫。\n百姓验证：湖北武穴市花桥镇水利站陈xx来信说：“陈巷村陈x和何xx均患痔疮多年，无钱去医院治疗，我用本条偏方仅几次就为他们治好了。”\n","categoryId":"000a43873e6-4e3b-4f9d-bb16-7ede9b04b54b","publisherId":null,"applicationId":null,"type":null,"tags":null,"url":"/2016/06/12873.html"}