{"id":"0005bd65a7c-a8b6-40e7-a1e3-293ae8e989bc","created":0,"title":"一招治好面瘫！","description":" 蝎子藏进鸡蛋、一招治好面瘫！    我这也有一个不错的偏方：是治疗受风后口歪眼斜的，也就是面瘫。不知道能不能派上用途，这是我亲身经历的。\n    方法很简单几元钱就能治愈：\n    用本地鸡蛋一个（打野鸡下的蛋），再去药店买全蝎，一定要全的头尾都不缺的。每天一个鸡蛋一个蝎子，把蝎子弄碎了把鸡蛋打个小洞。然后把蝎子放鸡蛋里，用纸封口，放火上烧熟。每天早起空腹吃。吃的过程中注意自己的脸部，如果好了就不能再吃了。轻者两天，严重的也就三到四天痊愈。\n    前提是不能针灸，否则就没有效果了。我曾经受风在医院花了几千元没有治好，邻居一位大妈给我这个方子，当时还不相信，后来实在没有办法才试用，没想到效果那么好。这个方子治一个保一个，我给四五个人提供过，都治好了。一般十天内的管用，时间长的没有给用过。\n   献方人：于老师\n\n \n","categoryId":"00019398938-d600-4efc-b0ad-f185419273f2","publisherId":null,"applicationId":null,"type":null,"tags":null,"url":"/2012/06/6717.html"}