{"id":"000173b9bac-9f45-44d5-a4fb-6d51b969d9c8","created":0,"title":"癫痫偏方-刘庆献方","description":"癫痫偏方\n　　求方回音　　在151期的偏方专栏里，电话尾号0604的读者，寻求癫痫偏方。这位读者，刚过30 岁，却已得了5年癫痫。一犯病，他就抽。每个月，都得来一次。因为这病，家里人不敢让他出去打工，怕出啥事。　　这几年，他吃了好多药，都是刺激大脑的。现在，不但癫痫没治好，脑袋也不好使了。求方信息登出后，好多读者，打来慰问电话。可对这个病，众多好心人，也束手无策。记者本以为，这个方子，难以寻到时，刘先生打来电话，推荐了个方子。刘先生说，这个方子，是食补，没有副作用，不刺激大脑，病人可放心食用。　　刘庆献方　　处方：　　猪膀胱（必须是公猪的）、江米　　用法：　　取一个公猪的膀胱，把里面尿液倒出来。将一把江米，放入猪膀胱里，然后将口扎上。扎好后，放在锅里蒸熟。蒸熟后，将其切成条，放在冰箱里保存。患者有时间，就吃一条。一个猪膀胱，最好在两天内吃完，然后再吃下一个。献方人称，他的母亲，吃了一年这东西。以前，每个月都犯一次病。如今，两年都没犯病了。　　治疗病例　　　　1984年，刘先生母亲，因为一点小事，和丈夫吵吵起来。那次争吵，挺激烈。双方，都杠上了，谁也不让谁。结果，刘母没说过刘父，一气之下，抽了。一看妻子这样，刘父吓坏了。再大的气，马上消了。他赶紧，给妻子掐人中。刘母救过来了，却留下了个毛病。一生气，就上下牙“打架”，血压升高。　　刘母，本来血压就高。生气后，血压更高，达到200 以上。刘先生说，有一次，母亲血压达到270。他买的电子血压剂，都被打爆了。这之后，每年春天，刘母都犯病。一年，至少犯三次。　　犯病之前，刘母有预感。只要心一慌，牙齿一打颤，过不了5分钟，就犯病。这时，家里人得马上将其送到医院。医院的治疗方法，就是打降压针。过了1996 年，刘母犯病次数更多了。每两个月，就得犯一次病。　　那时，刘母已经60多岁了。刘先生说，母亲犯病时，就像躺在弹簧床上似的，身体直抖。他们家里人，又是按腿，又是按手，啥方法都没用。只能是送医院，降压药吃着、吸氧机开着、心电图监控着。　　这些年里，刘先生领着母亲，北京、上海的各大医院，都看过了。可不管是西医、中医，还是路边的游医，都治不好这病。别的癫痫病人，犯病时抽，神智不清，口吐白沫。可刘母犯病时，这些症状都没有。　　有的医生说，刘母这病，是肾上腺神经放电疾病。这些年来，很多医院，都是按此病治疗。前年年初，刘先生一位姓杨的阿姨，从老家淘来一个方子。杨阿姨说，这个方子，是老家专治癫痫的。　　刘先生，一直不信任偏方。他寻思，大医院的知名大夫，都治不好的病，偏方能好使吗？再者，他认为，母亲的病，和癫痫还不太一样。抱着试试看的心理，他让母亲用了这个偏方。他到杀猪的地方，一次买七八个猪膀胱，放了江米后，蒸熟给母亲吃。这东西，有股尿骚味。　　虽然难吃，母亲为了不让儿女操心，也是坚持天天吃。吃了一年后，奇迹出现了。一年内，她都没再犯病。如今，已经停吃此方两年了，刘母还是啥事没有。刘先生觉得，此方是专治癫痫的，正好有人求方，他就献出来，让那位求方人试试。\n\n共2页    1 2 下一页 尾页\n\n　　药理分析\n　　此方，为啥能治癫痫病，献方人说不清。记者查寻了相关资料后发现，江米有补虚、补血和治疗气短无力等症的功效。医师孟诜说，此物可治吐逆不止。所以，从癫痫患者，口吐白沫中可发现，此物可治口吐白沫。而猪膀胱，可治消渴无度。二者结合，产生了哪种化学反应，记者问了民间老中医，他们也解释不清。　　温馨提示　　猪膀胱的外表面，可以洗净。里面，倒完尿液后，绝对不能洗。江米的量，不要太多。只要蒸熟后，能将猪膀胱撑起即可。\n共2页   首页 上一页 1 2","categoryId":"00019398938-d600-4efc-b0ad-f185419273f2","publisherId":null,"applicationId":null,"type":null,"tags":null,"url":"/2012/12/8428.html"}