{"id":"0003c08e32c-70be-4f11-98ad-deefe58c3af2","created":0,"title":"用此法按摩可以治愈鼻息肉","description":"　　鼻息肉为常见鼻病，好发于双侧筛窦，单侧者较少。多因慢性鼻部炎症的长期刺激导致鼻部的变态反应等逐渐形成。临床以持续性鼻塞，嗅觉减退，闭塞性鼻音，眨眼时打鼾为主要特点。若息肉阻塞鼻窦引流，可引起鼻窦炎；阻塞咽鼓管咽口，可引起耳鸣和听力减退。\n　　赵妪，今年84岁。1974年鼻生息肉，痰液带血，左鼻孔堵塞不通。曾进行过2次切除手术，而术后息肉复发。\n　　患者自用双手中指压在鼻息肉对应外侧，睡前进行轻轻揉搓和按摩100余次，头几用鼻中有脓血样液体流出，1月后左鼻孔即能通气，脓液逐渐消失，自感轻松，2个月后恢复正常。以后患者仍不断进行自我按摩，至今已11年，未见复发。\n　　荐方人：宁夏食品检验所 赵杰\n　　百姓验证：\n　　广东台山台城镇富华新村257号甄xx，男，53岁。他来信说：“我爱人患鼻息肉多年，手术两次又复发。我用本条偏方为她治疗，很见效，原来鼻息肉堵住鼻腔，现已很少了。”\n　　四川彭山西铁分局陈xx，女，72岁。他来信说：“邻居李嫂的儿子患有鼻息肉，我用本条偏方和《用清凉油治鼻息肉有奇效》为她治愈，已有1年没复发了。”\n　　提示：本方经许许多多患者自疗验证，疗效较好，大多数病人得到了缓解或治愈，因此，本方堪称佳效良方。\n","categoryId":"000d3e70cea-06ab-418e-9f4c-aa7eba26fb60","publisherId":null,"applicationId":null,"type":null,"tags":null,"url":"/2013/10/10105.html"}