{"id":"000bc37bf64-e511-46dd-a05d-df29d24623c4","created":0,"title":"治脑血管病现代妙方","description":"治脑血管病现代妙方\n1、  氟桂利嗪治脑血管病病后二便失禁用法：在常规治疗同时，给氟桂利嗪每次5毫克，每晚一次，连服15--30天。疗效：治疗多例，服一次即见效，服20天后全部治愈。2、  金刚烷胺治脑梗后意识低下用法：金刚烷胺每次50--100毫克，每日服2--3次，连服4--8周。疗效：效果显著。3、  尼莫地平治脑血管痉挛用法：尼莫地平，每次30--40毫克，每日三次服，服7--10天。疗效：显效率97.2%4、  山莨菪碱治脑血栓用法：山莨菪碱20--40毫克，加0.9%生理盐水250--500毫升，静脉点滴，每日一次，有效后改为口服，每次10毫克，每日三次服，15天为一个疗程。疗效：有效率92.2% 5、  甘露醇治脑血栓用法：20%甘露醇250毫升，静脉点滴，每日一次，重者每次加地 塞米松5--10毫克，二周为疗程。疗效：有效率91.6% 6、  阿司匹林防治脑缺血发作用法：阿司匹林，每次50--75毫克，每日三次服，服一个月。疗效：有效率100%7 脑力隆治脑缺血发作用法：每次1粒，每天服一次，服一个月后改为每天三次服。疗效：治愈率88%，显效率9%，共97%\n","categoryId":"000d222fa3e-78c1-4004-91af-179e7603ae85","publisherId":null,"applicationId":null,"type":null,"tags":null,"url":"/2015/12/12401.html"}