{"id":"00019c32d22-0547-42ea-a4f7-755be33b13eb","created":0,"title":"用穴位贴敷法治脑囊虫很有效","description":"用穴位贴敷法治脑囊虫很有效\n \n配方及用法：砒石（信石、人言、红矾）10克，巴豆7个，斑蝥3个，珍珠1只（大），轻粉3克，银珠15克，狼毒50克（或蜂蜜适量）。先将斑蝥去头、足、翅；巴豆去皮，焙干研末；砒石、轻粉、银珠研细末；新鲜狼毒捣成泥状。诸药调和捣匀而形成糊状即可外敷，分敷于双太阳穴（外眼角斜上方）、印堂穴（双眉中间）、神阙穴（肚脐上）。外敷约3~4小时，察看皮肤，以出米粒丘疹为度，然后除去外敷药贴，即可达到治疗效果。\n \n注意：使用本偏方药外贴一次未愈者可于半个月后再敷贴一次。禁忌小米饭、荞面、辛、辣、甜、牛羊肉类一周以上。皮肤易起水泡、易感染者禁用。敷药用完后深埋土中。\n疗效：共治疗3例，皆治愈。\n引自：《亲献中药外治偏方秘方》\n百姓验证\n辽宁宽甸县西门外教师高某患有癫痫病多年，反复大发作，每月发作数次。服苯妥英钠等抗癫痫药物无效，后经沈阳医科大学附属医院确诊为脑囊虫病。依据本条偏方治疗，敷药一周后癫痫发作次数明显减少，头痛减轻。故半月后又外敷药贴一次，其后癫痫病停发，至今已获痊愈。\n","categoryId":"000d222fa3e-78c1-4004-91af-179e7603ae85","publisherId":null,"applicationId":null,"type":null,"tags":null,"url":"/2014/11/11412.html"}