{"id":"0005feffd93-5f6d-415c-969a-b58d78b5988a","created":0,"title":"献出动脉炎一方","description":"动脉炎是俗称，区别于静脉曲张。古时称为“脱骨疽”（现在叫动脉栓塞性坏疽），指的是脚上的动脉搏动消失，血液停止流通，最后脚趾一个个坏死脱落，双脚冰冷，疼痛异常。往往只有截肢。\n我给朋友们献上一方，有缘看到这篇日志的朋友，有福了，你可以免去截肢之苦了：元参 90克 当归60克 金银花90克 甘草30克四位药放于大砂锅（或者搪瓷盆）里，倒上四大碗水，煎到盛一碗水的时候倒出来，再用两碗水煎药渣，剩半碗时倒出，混合，分两次温服。晚饭后服一次，第二天早晨服一次。（15—20副左右就完全好了，一般5—7副疼痛感消失，20副左右两脚温暖，就痊愈了。）\n","categoryId":"000d222fa3e-78c1-4004-91af-179e7603ae85","publisherId":null,"applicationId":null,"type":null,"tags":null,"url":"/2012/07/7007.html"}